{
  "candidate": {
    "bundle_rel": "ta/binance/chat_bundle_latest.json",
    "bundle_sha256": "e1575389e375aef9e34e091c9425705aecbf11204c5c314b1c3acf212ba43c7d",
    "report_rel": "ta/binance/chat_report_latest.md",
    "report_sha256": "8f7edccc7c9781bad131726a5ab34843235670b6abe4d4236c7f1eb1a5ab9060"
  },
  "errors": [],
  "generated_utc": "2026-02-19T21:56:09Z",
  "kept_last_good": false,
  "published": {
    "bundle_rel": "ta/binance/chat_bundle_latest.json",
    "bundle_sha256": "e1575389e375aef9e34e091c9425705aecbf11204c5c314b1c3acf212ba43c7d",
    "report_rel": "ta/binance/chat_report_latest.md",
    "report_sha256": "8f7edccc7c9781bad131726a5ab34843235670b6abe4d4236c7f1eb1a5ab9060"
  },
  "quality": "OK",
  "schema": "iron.build_status.v1",
  "sources": {
    "contract": {
      "path": "iron/IRON_CONTRACT_CURRENT.json",
      "sha256": "447e0370aa9935021e3a665877d4bed31a7955d8ae3c3fb18a50090bf5ca5f77"
    },
    "state": {
      "path": "docs/ta/binance/state_btc_eth_full_latest.json",
      "sha256": "46239146009ab2bce20197368b65af9b996f799e1f032f9577f7fc77f6da36ab",
      "source": "ta_state_pivots_atr_full",
      "updated_utc": "2026-02-19T21:56:09.665573Z"
    }
  },
  "verify": {
    "errors": [],
    "ran": true,
    "target": {
      "bundle_rel": "ta/binance/chat_bundle_latest.json",
      "report_rel": "ta/binance/chat_report_latest.md"
    },
    "warnings": []
  },
  "warnings": []
}
