{"updated_utc":"2026-02-12T21:43:45.025759Z","symbol":"AAVEUSDT","tf":"W1","tail_n":520,"chunk_size":260,"parts":[{"file":"AAVEUSDT_W1_tail520_p000.json","count":260,"from_open_time_ms":1602460800000,"to_close_time_ms":1759708799999,"url":"https://andreibaulin.github.io/ohlcv-feed/ohlcv/binance/AAVEUSDT_W1_tail520_p000.json?v=2026-02-12T21:43:45.025759Z"},{"file":"AAVEUSDT_W1_tail520_p001.json","count":18,"from_open_time_ms":1759708800000,"to_close_time_ms":1770595199999,"url":"https://andreibaulin.github.io/ohlcv-feed/ohlcv/binance/AAVEUSDT_W1_tail520_p001.json?v=2026-02-12T21:43:45.025759Z"}],"total":278,"schema":"[open_time_ms, open, high, low, close, volume, close_time_ms]"}
