{"updated_utc":"2026-02-16T14:02:28.269357Z","symbol":"BTCUSDT","tf":"D1","tail_n":2000,"chunk_size":200,"parts":[{"file":"BTCUSDT_D1_tail2000_p000.json","count":200,"from_open_time_ms":1598486400000,"to_close_time_ms":1615766399999,"url":"https://andreibaulin.github.io/ohlcv-feed/ohlcv/binance/BTCUSDT_D1_tail2000_p000.json?v=2026-02-16T14:02:28.269357Z"},{"file":"BTCUSDT_D1_tail2000_p001.json","count":200,"from_open_time_ms":1615766400000,"to_close_time_ms":1633046399999,"url":"https://andreibaulin.github.io/ohlcv-feed/ohlcv/binance/BTCUSDT_D1_tail2000_p001.json?v=2026-02-16T14:02:28.269357Z"},{"file":"BTCUSDT_D1_tail2000_p002.json","count":200,"from_open_time_ms":1633046400000,"to_close_time_ms":1650326399999,"url":"https://andreibaulin.github.io/ohlcv-feed/ohlcv/binance/BTCUSDT_D1_tail2000_p002.json?v=2026-02-16T14:02:28.269357Z"},{"file":"BTCUSDT_D1_tail2000_p003.json","count":200,"from_open_time_ms":1650326400000,"to_close_time_ms":1667606399999,"url":"https://andreibaulin.github.io/ohlcv-feed/ohlcv/binance/BTCUSDT_D1_tail2000_p003.json?v=2026-02-16T14:02:28.269357Z"},{"file":"BTCUSDT_D1_tail2000_p004.json","count":200,"from_open_time_ms":1667606400000,"to_close_time_ms":1684886399999,"url":"https://andreibaulin.github.io/ohlcv-feed/ohlcv/binance/BTCUSDT_D1_tail2000_p004.json?v=2026-02-16T14:02:28.269357Z"},{"file":"BTCUSDT_D1_tail2000_p005.json","count":200,"from_open_time_ms":1684886400000,"to_close_time_ms":1702166399999,"url":"https://andreibaulin.github.io/ohlcv-feed/ohlcv/binance/BTCUSDT_D1_tail2000_p005.json?v=2026-02-16T14:02:28.269357Z"},{"file":"BTCUSDT_D1_tail2000_p006.json","count":200,"from_open_time_ms":1702166400000,"to_close_time_ms":1719446399999,"url":"https://andreibaulin.github.io/ohlcv-feed/ohlcv/binance/BTCUSDT_D1_tail2000_p006.json?v=2026-02-16T14:02:28.269357Z"},{"file":"BTCUSDT_D1_tail2000_p007.json","count":200,"from_open_time_ms":1719446400000,"to_close_time_ms":1736726399999,"url":"https://andreibaulin.github.io/ohlcv-feed/ohlcv/binance/BTCUSDT_D1_tail2000_p007.json?v=2026-02-16T14:02:28.269357Z"},{"file":"BTCUSDT_D1_tail2000_p008.json","count":200,"from_open_time_ms":1736726400000,"to_close_time_ms":1754006399999,"url":"https://andreibaulin.github.io/ohlcv-feed/ohlcv/binance/BTCUSDT_D1_tail2000_p008.json?v=2026-02-16T14:02:28.269357Z"},{"file":"BTCUSDT_D1_tail2000_p009.json","count":199,"from_open_time_ms":1754006400000,"to_close_time_ms":1771199999999,"url":"https://andreibaulin.github.io/ohlcv-feed/ohlcv/binance/BTCUSDT_D1_tail2000_p009.json?v=2026-02-16T14:02:28.269357Z"}],"total":1999,"schema":"[open_time_ms, open, high, low, close, volume, close_time_ms]"}
